Metadata-Version: 2.1
Name: OpenAnnotate
Version: 0.0.5
Summary: A python package for efficiently annotating the chromatin accessibility of genomic regions.
Home-page: https://github.com/ZjGaothu/OpenAnnotate
Author: Gaozj
Author-email: 3193346402@qq.com
License: Apache License 2.0
Project-URL: Web, http://health.tsinghua.edu.cn/openness/anno/
Platform: UNKNOWN
